{
  "1.0.0a5": {
    "description": "minor internal changes",
    "date": "2019-07-06T17:13:54.473706",
    "changes": [
      "refactored internal structure of SeqDB to use networkx.DiGraph"
    ]
  },
  "1.0.0a4": {
    "description": "",
    "date": "2019-07-05T16:10:50.061058",
    "changes": []
  },
  "1.0.0a3": {
    "description": "updated package management and version",
    "date": "2019-07-05T11:14:35.956014",
    "changes": [
      "added keats pkg management",
      "verison maintained in __version__.py"
    ]
  },
  "1.0.0a6": {
    "description": "change to parsed results in JSON",
    "date": "2019-07-07T08:03:56.710460",
    "changes": [
      "Added origin_key and replaced origin_sequence_id with origin_record_id"
    ]
  }
}